{
  "success": true,
  "data": {
    "users": [
      {
        "nickname": "OKX官方钱包",
        "addresses": [
          "0xa1d2c4533d867ce4623681f68df84d9cad73cb6b"
        ],
        "initialBalanceTotal": 131452001.01,
        "currentBalances": [
          148830139.33298212
        ],
        "totalBalance": 148830139.33298212,
        "percentage": 13.220139814882014,
        "lpBalances": [
          0
        ],
        "totalLPBalance": 0,
        "poolDOGHoldings": 0
      },
      {
        "nickname": "哈密瓜",
        "addresses": [
          "0x3069b7e82a1b459047b3e356db8139cdc0ff6747"
        ],
        "initialBalanceTotal": 853000000,
        "currentBalances": [
          9292419.50999737
        ],
        "totalBalance": 9292419.50999737,
        "percentage": 8.106009929316068,
        "lpBalances": [
          3.588855003398986
        ],
        "totalLPBalance": 3.588855003398986,
        "poolDOGHoldings": 912851845.1870687
      },
      {
        "nickname": "哪有赌狗天天输",
        "addresses": [
          "0x0e7e42f4ff895e8f8a3933ec8d6238b9f436be1f"
        ],
        "initialBalanceTotal": 688704606.9406,
        "currentBalances": [
          94809415.11197154
        ],
        "totalBalance": 94809415.11197154,
        "percentage": -52.615349597960794,
        "lpBalances": [
          0.9102579706327414
        ],
        "totalLPBalance": 0.9102579706327414,
        "poolDOGHoldings": 231530855.18957004
      },
      {
        "nickname": "齐天大圣",
        "addresses": [
          "0xe4f0fbd632ad310d146eaeac8624b4f81278d1e8"
        ],
        "initialBalanceTotal": 626317899.6,
        "currentBalances": [
          58355907.22224093
        ],
        "totalBalance": 58355907.22224093,
        "percentage": -10.05039636060582,
        "lpBalances": [
          1.9854525611752674
        ],
        "totalLPBalance": 1.9854525611752674,
        "poolDOGHoldings": 505014560.9905379
      },
      {
        "nickname": "小狗旺旺",
        "addresses": [
          "0x1e3a1e33d82a21e04a2d269dbe4f0fcd324043be",
          "0x8199d7f2a479c4e223bc91f0d1ad922956884ac4",
          "0xe4aae38402ab4749f518117bf38f84ff814b860c"
        ],
        "initialBalanceTotal": 483285115,
        "currentBalances": [
          103195390.23967603,
          10582700.66897921,
          15098058.762219898
        ],
        "totalBalance": 128876149.67087513,
        "percentage": -17.966586019961742,
        "lpBalances": [
          0.18165568998946763,
          0.5316196458747726,
          0.3387055551102772
        ],
        "totalLPBalance": 1.0519808909745176,
        "poolDOGHoldings": 267579129.42097884
      },
      {
        "nickname": "狂飚",
        "addresses": [
          "0x362ead7ca70e0143eaf28f0e9e741619acc369ea"
        ],
        "initialBalanceTotal": 438322123.05,
        "currentBalances": [
          252248439.72592515
        ],
        "totalBalance": 252248439.72592515,
        "percentage": 33.033598642764474,
        "lpBalances": [
          1.3007966265396902
        ],
        "totalLPBalance": 1.3007966265396902,
        "poolDOGHoldings": 330867254.2148561
      },
      {
        "nickname": "闲云",
        "addresses": [
          "0x6f58b15911cd025e0ee807704579480fb89b8a1c"
        ],
        "initialBalanceTotal": 302072896,
        "currentBalances": [
          1e-18
        ],
        "totalBalance": 1e-18,
        "percentage": -57.7038938042881,
        "lpBalances": [
          0.5023053012214617
        ],
        "totalLPBalance": 0.5023053012214617,
        "poolDOGHoldings": 127765072.88062236
      },
      {
        "nickname": "光",
        "addresses": [
          "0x83e31de2cdbe3099eb7b8c7e6b6e10a284efb100"
        ],
        "initialBalanceTotal": 298158269,
        "currentBalances": [
          100574397.31738004
        ],
        "totalBalance": 100574397.31738004,
        "percentage": -24.643102049863444,
        "lpBalances": [
          0.48792927902790256
        ],
        "totalLPBalance": 0.48792927902790256,
        "poolDOGHoldings": 124108425.18284358
      },
      {
        "nickname": "道哥币赢",
        "addresses": [
          "0xb05db08b8067ee5007d7bbb7690afd391048b4cf",
          "0xe49c97662513c138b1701EEbFd02c955C025e16E",
          "0x6392b37404e5c2609a19445bf91b71e699a3f98f"
        ],
        "initialBalanceTotal": 282000000,
        "currentBalances": [
          0,
          30065426.6846456,
          255.15633854673072
        ],
        "totalBalance": 30065681.840984147,
        "percentage": -21.6308122789498,
        "lpBalances": [
          0.5,
          0,
          0.25065802631452494
        ],
        "totalLPBalance": 0.7506580263145249,
        "poolDOGHoldings": 190935427.53237742
      },
      {
        "nickname": "云淡风轻",
        "addresses": [
          "0x4a4791dd6ed2ff2a3307ee34dad8e94a2c02c447"
        ],
        "initialBalanceTotal": 255816946.36,
        "currentBalances": [
          162684422.77161634
        ],
        "totalBalance": 162684422.77161634,
        "percentage": -17.202340423259443,
        "lpBalances": [
          0.19313776863154158
        ],
        "totalLPBalance": 0.19313776863154158,
        "poolDOGHoldings": 49126021.61514947
      },
      {
        "nickname": "旺旺",
        "addresses": [
          "0x893f3a08f24b9f394e32398a85be8a04a306e810"
        ],
        "initialBalanceTotal": 250000000,
        "currentBalances": [
          148736082.1049629
        ],
        "totalBalance": 148736082.1049629,
        "percentage": -1.9742387671138049,
        "lpBalances": [
          0.3787124696422028
        ],
        "totalLPBalance": 0.3787124696422028,
        "poolDOGHoldings": 96328320.97725262
      },
      {
        "nickname": "大白",
        "addresses": [
          "0xc374acd9a7683aa9e6c48586370b6d8245ee21cc"
        ],
        "initialBalanceTotal": 243000000,
        "currentBalances": [
          39.848332056914735
        ],
        "totalBalance": 39.848332056914735,
        "percentage": -47.023473188159464,
        "lpBalances": [
          0.5061103700152751
        ],
        "totalLPBalance": 0.5061103700152751,
        "poolDOGHoldings": 128732920.30444044
      },
      {
        "nickname": "2025国泰民安",
        "addresses": [
          "0x359ba4ff0efab569ed1c65d2bd69d08e4aa67a88",
          "0x6050df3e868d6baea660f6c0ad49930bc5ad66c3"
        ],
        "initialBalanceTotal": 205343380,
        "currentBalances": [
          10496767.587873306,
          7933321.770114834
        ],
        "totalBalance": 18430089.35798814,
        "percentage": -39.88656382333563,
        "lpBalances": [
          0.2239942922966296,
          0.18884555550410015
        ],
        "totalLPBalance": 0.41283984780072974,
        "poolDOGHoldings": 105008872.32131726
      },
      {
        "nickname": "焚石",
        "addresses": [
          "0x67514d3219fd78AA1e6d528fBa32A589a167968c",
          "0x97bbaa519ee28f8cb36fe7d9a4e4683998fc8200"
        ],
        "initialBalanceTotal": 200000000,
        "currentBalances": [
          15408.593546775048,
          0
        ],
        "totalBalance": 15408.593546775048,
        "percentage": -99.9922957032266,
        "lpBalances": [
          0,
          0
        ],
        "totalLPBalance": 0,
        "poolDOGHoldings": 0
      },
      {
        "nickname": "leezerofly",
        "addresses": [
          "0x82ba6bf0a655344e6c8863af13188658a4894bd2",
          "0xdbb4655a567e205ee7490ab18aa30c7f043b65b2"
        ],
        "initialBalanceTotal": 186210563,
        "currentBalances": [
          0.023641461820611994,
          3.7896088899289366
        ],
        "totalBalance": 3.8132503517495486,
        "percentage": -1.693973456436035,
        "lpBalances": [
          0.5621813045872177,
          0.15749973539042514
        ],
        "totalLPBalance": 0.7196810399776429,
        "poolDOGHoldings": 183056201.67644954
      },
      {
        "nickname": "williams",
        "addresses": [
          "0x7f41b8c7510da4e26dd1ddb0895cf3a82795180f"
        ],
        "initialBalanceTotal": 179190000,
        "currentBalances": [
          0
        ],
        "totalBalance": 0,
        "percentage": -56.41866093486866,
        "lpBalances": [
          0.30702232358803394
        ],
        "totalLPBalance": 0.30702232358803394,
        "poolDOGHoldings": 78093401.47080885
      },
      {
        "nickname": "吉姆熊猫",
        "addresses": [
          "0x4d6ae7eb9c767436fdc91ad1498d7c3ded176afc"
        ],
        "initialBalanceTotal": 174750118,
        "currentBalances": [
          0
        ],
        "totalBalance": 0,
        "percentage": -49.64721255031152,
        "lpBalances": [
          0.3459366772634648
        ],
        "totalLPBalance": 0.3459366772634648,
        "poolDOGHoldings": 87991555.48461981
      },
      {
        "nickname": "LV",
        "addresses": [
          "0xb244df3bEb6D7531Ea4b55435f444bff318BdD92"
        ],
        "initialBalanceTotal": 150000000,
        "currentBalances": [
          62568031.22131931
        ],
        "totalBalance": 62568031.22131931,
        "percentage": 14.544413786752184,
        "lpBalances": [
          0.4295081934277963
        ],
        "totalLPBalance": 0.4295081934277963,
        "poolDOGHoldings": 109248589.45880896
      },
      {
        "nickname": "韭菜人生",
        "addresses": [
          "0x48388fa2485ee89bbcc3898c56f3482abd338e5d",
          "0xcd43f9e7ee6af34429e003b4e64dfe41c3444465"
        ],
        "initialBalanceTotal": 140000000,
        "currentBalances": [
          8299676.749747194,
          3.83587823232e-7
        ],
        "totalBalance": 8299676.749747578,
        "percentage": 78.44806876147592,
        "lpBalances": [
          0.9495600083741454,
          0
        ],
        "totalLPBalance": 0.9495600083741454,
        "poolDOGHoldings": 241527619.5163187
      },
      {
        "nickname": "羽辰",
        "addresses": [
          "0xf13d79bae5886b189a3c55c0bb81a0dcfdcac8c5",
          "0x008065ff70b71e21482d3fab61ffb6df6e0b4a89"
        ],
        "initialBalanceTotal": 131000000,
        "currentBalances": [
          1e-18,
          37.496654558161055
        ],
        "totalBalance": 37.496654558161055,
        "percentage": 0.2035256699846901,
        "lpBalances": [
          0,
          0.5160713964209807
        ],
        "totalLPBalance": 0.5160713964209807,
        "poolDOGHoldings": 131266581.13102539
      },
      {
        "nickname": "zhengch",
        "addresses": [
          "0x4dbd81e45023a64af8d75a7b94a8e04fe17f9031",
          "0xfc250ce0ec2f48f45050043e3bd0ee9b940383a3",
          "0xc865e2efe116fdb67575cdd5e3bbe594abedbba9"
        ],
        "initialBalanceTotal": 125545211,
        "currentBalances": [
          43105674.47324813,
          6572586.207304896,
          19059387.14738328
        ],
        "totalBalance": 68737647.8279363,
        "percentage": -11.070208248516678,
        "lpBalances": [
          0.04780926955057456,
          0.07260623188751616,
          0.04828195357434844
        ],
        "totalLPBalance": 0.16869745501243916,
        "poolDOGHoldings": 42909446.86832402
      },
      {
        "nickname": "沙漠绿洲",
        "addresses": [
          "0x750f9a6ae2b57e0c3ea9f172fe8e48422d4f1c78",
          "0x6d42ED10e319B544941a345e3Aad989079F258E6"
        ],
        "initialBalanceTotal": 120000000,
        "currentBalances": [
          67461880.36845319,
          6046552.272497206
        ],
        "totalBalance": 73508432.6409504,
        "percentage": -18.01445917302445,
        "lpBalances": [
          0,
          0.09779238140240555
        ],
        "totalLPBalance": 0.09779238140240555,
        "poolDOGHoldings": 24874216.351420265
      },
      {
        "nickname": "城",
        "addresses": [
          "0x78147ca45b59a3e96076fcbf68c3a99260d67e0b",
          "0x5ae833c58febd21c4c99fa78407b18e3d3e83b95"
        ],
        "initialBalanceTotal": 120000000,
        "currentBalances": [
          30003740.72046716,
          30038819.505110864
        ],
        "totalBalance": 60042560.225578025,
        "percentage": -19.648891760888894,
        "lpBalances": [
          0.06457085911082522,
          0.07845139603935113
        ],
        "totalLPBalance": 0.14302225515017636,
        "poolDOGHoldings": 36378769.66135531
      },
      {
        "nickname": "如果 爱",
        "addresses": [
          "0x21fb80e72af9ca930cfe744906adfbd24460b876",
          "0x87291db3d8f08c4cad35744f45150717fd10c310"
        ],
        "initialBalanceTotal": 119725915,
        "currentBalances": [
          17417774.92990524,
          5033260.1458222885
        ],
        "totalBalance": 22451035.07572753,
        "percentage": -21.38135811762521,
        "lpBalances": [
          0.04471882688827686,
          0.23707306082904459
        ],
        "totalLPBalance": 0.28179188771732144,
        "poolDOGHoldings": 71675853.2785189
      },
      {
        "nickname": "貳大爺",
        "addresses": [
          "0xA029A47599Cebe487E2E69F61dc97058D449EAe4",
          "0x80745ccFFB3C50f7CC558464414fc9A940384A36",
          "0x5b2bec6f1bc0dce46669e60f3db1efc3a71a11ab"
        ],
        "initialBalanceTotal": 118862385.9,
        "currentBalances": [
          0,
          0,
          0
        ],
        "totalBalance": 0,
        "percentage": -74.28025283528626,
        "lpBalances": [
          0,
          0,
          0.12018956216659318
        ],
        "totalLPBalance": 0.12018956216659318,
        "poolDOGHoldings": 30571105.12742636
      },
      {
        "nickname": "繁星社区~甘",
        "addresses": [
          "0x8D15e83964B99e2FC6995cA6D308D8501fcE57B3"
        ],
        "initialBalanceTotal": 118710390,
        "currentBalances": [
          9869322.6063763
        ],
        "totalBalance": 9869322.6063763,
        "percentage": -5.731347643429514,
        "lpBalances": [
          0.40115742766925133
        ],
        "totalLPBalance": 0.40115742766925133,
        "poolDOGHoldings": 102037362.25385271
      },
      {
        "nickname": "星星之火",
        "addresses": [
          "0x8be8026CF67CA39ce6863796908ED68bf9eE948E"
        ],
        "initialBalanceTotal": 118478429,
        "currentBalances": [
          75812783.84984937
        ],
        "totalBalance": 75812783.84984937,
        "percentage": 7.098604245211957,
        "lpBalances": [
          0.2008039041093249
        ],
        "totalLPBalance": 0.2008039041093249,
        "poolDOGHoldings": 51075959.94080506
      },
      {
        "nickname": "东风（叶军民）",
        "addresses": [
          "0x6D5F722b0BeB821a5337F505cEF03888795E1d56",
          "0xBaA3be34b770DDf3DF7d10360e594233F106D2CC"
        ],
        "initialBalanceTotal": 118000000,
        "currentBalances": [
          7946149.133626892,
          11709247.714495307
        ],
        "totalBalance": 19655396.848122198,
        "percentage": -2.2134236981525635,
        "lpBalances": [
          0.32981895165722713,
          0.04655209690680814
        ],
        "totalLPBalance": 0.37637104856403525,
        "poolDOGHoldings": 95732763.18805778
      },
      {
        "nickname": "慕兮",
        "addresses": [
          "0x92498505a053c3a74d52ff76194ec2249412ab45",
          "0x90c4d53d343b76fe2c716448083b9dc6a1ff23c9",
          "0xba04e27872c740ab04c24b2c67f9b2ee9f202ae9"
        ],
        "initialBalanceTotal": 115532138,
        "currentBalances": [
          0.015970634180396254,
          0.013837285608685797,
          0.00666794409330805
        ],
        "totalBalance": 0.0364758638823901,
        "percentage": 583.9652627770831,
        "lpBalances": [
          0.49233696244431857,
          1.4000254448648632,
          1.2142886122370806
        ],
        "totalLPBalance": 3.1066510195462627,
        "poolDOGHoldings": 790199691.2272065
      },
      {
        "nickname": "以马内利",
        "addresses": [
          "0x636B9803BB09199B9102CfBCc441BFa592B653dd",
          "0x344650ee072610438636d1A40dC16dC93de576F8"
        ],
        "initialBalanceTotal": 111491843,
        "currentBalances": [
          18908.01371085838,
          34954.44794796091
        ],
        "totalBalance": 53862.46165881929,
        "percentage": 4.997077861681294,
        "lpBalances": [
          0.2686148222710552,
          0.1914044753530424
        ],
        "totalLPBalance": 0.4600192976240976,
        "poolDOGHoldings": 117009314.74247465
      },
      {
        "nickname": "吴坚不摧",
        "addresses": [
          "0xfd60cfbfe9223f6a15a5935f27663dcb98f96d7a",
          "0xd7756a84530a750cfd0ccaaac659826a07037f88",
          "0x8929ace29737b4bcee0b856c358fb78675874434",
          "0x7c05f0c1bba888859e05c995c9f31531088da0eb"
        ],
        "initialBalanceTotal": 110261409,
        "currentBalances": [
          136101.10445472514,
          3787.1680781185114,
          41676.03400560672,
          91657.24151426417
        ],
        "totalBalance": 273221.54805271456,
        "percentage": 159.86048749530218,
        "lpBalances": [
          0,
          0.5692154906307392,
          0.22012647523128684,
          0.33605327680284064
        ],
        "totalLPBalance": 1.1253952426648666,
        "poolDOGHoldings": 286252613.39853626
      },
      {
        "nickname": "郁姐",
        "addresses": [
          "0x953525b75b33aa0c5fffb743e1dcfad1cdfaa956"
        ],
        "initialBalanceTotal": 108236377,
        "currentBalances": [
          23508482.56543794
        ],
        "totalBalance": 23508482.56543794,
        "percentage": -19.15551654321733,
        "lpBalances": [
          0.2515934511932253
        ],
        "totalLPBalance": 0.2515934511932253,
        "poolDOGHoldings": 63994657.33254798
      },
      {
        "nickname": "小小",
        "addresses": [
          "0xEA0f8b9271b29bd9333B5a4116db099E88c30C50"
        ],
        "initialBalanceTotal": 106600002,
        "currentBalances": [
          85530838.19323486
        ],
        "totalBalance": 85530838.19323486,
        "percentage": 0.7510205390672984,
        "lpBalances": [
          0.08598040118385668
        ],
        "totalLPBalance": 0.08598040118385668,
        "poolDOGHoldings": 21869751.71643129
      },
      {
        "nickname": "无鱼",
        "addresses": [
          "0x6d46361ed4fbc6cc69766a8f61ab7765cf765ca2",
          "0x98519325a97536de1f048673001fdefbf2c03009",
          "0xf8fb3beccb0261af3acaec171235807981cbeb1b"
        ],
        "initialBalanceTotal": 105940786,
        "currentBalances": [
          21335462.1073137,
          5130762.006781707,
          0
        ],
        "totalBalance": 26466224.114095405,
        "percentage": -15.378156639117503,
        "lpBalances": [
          0.11140662383838332,
          0.09379168167707225,
          0.043203434145761097
        ],
        "totalLPBalance": 0.24840173966121665,
        "poolDOGHoldings": 63182821.87011233
      },
      {
        "nickname": "成成",
        "addresses": [
          "0x983191d9Ad653C0fD00DCA01AA6fa9165bA3Abfc",
          "0xbE2A9850f49B763782384990C4B3f73Ab489ab49"
        ],
        "initialBalanceTotal": 105736479,
        "currentBalances": [
          295837.75134230306,
          0
        ],
        "totalBalance": 295837.75134230306,
        "percentage": 4.887032865144865,
        "lpBalances": [
          0.21117424503943957,
          0.22367850782675633
        ],
        "totalLPBalance": 0.4348527528661959,
        "poolDOGHoldings": 110608017.7278347
      },
      {
        "nickname": "锋人院",
        "addresses": [
          "0x889015d2d53c53474c276dcfaf614b294edafc97"
        ],
        "initialBalanceTotal": 103121334,
        "currentBalances": [
          0
        ],
        "totalBalance": 0,
        "percentage": -51.400546996183586,
        "lpBalances": [
          0.19703143408044696
        ],
        "totalLPBalance": 0.19703143408044696,
        "poolDOGHoldings": 50116404.25423856
      },
      {
        "nickname": "@野火（蒙）",
        "addresses": [
          "0x1ac9acbaffe938b4cb7fbb0eb88f641cfb690837"
        ],
        "initialBalanceTotal": 102286355,
        "currentBalances": [
          127277208.87068534
        ],
        "totalBalance": 127277208.87068534,
        "percentage": 24.432245992816284,
        "lpBalances": [
          0
        ],
        "totalLPBalance": 0,
        "poolDOGHoldings": 0
      },
      {
        "nickname": "清雅",
        "addresses": [
          "0x3872db5cf33c46e06385fecbbe06f0808bc580bf",
          "0xdd405cb98a5bb14727bd5dc0270a955a62c44c7f"
        ],
        "initialBalanceTotal": 101701252,
        "currentBalances": [
          0.01187485695501878,
          0.023927901849667654
        ],
        "totalBalance": 0.03580275880468643,
        "percentage": 164.15458622873157,
        "lpBalances": [
          0.8368290811413914,
          0.21935609849429216
        ],
        "totalLPBalance": 1.0561851796356836,
        "poolDOGHoldings": 268648521.3742368
      },
      {
        "nickname": "memecoin",
        "addresses": [
          "0x7855F676b7B2A370FB7E6eD74Bde705fdc890230",
          "0x9F3d2b0C438c7A1E8FAcadFD878b7caE2718205F",
          "0x196d31736a1F52FB65a15218718F522C38e52eCd",
          "0xAb0DD2b23031E73f47a7C9B1cd6715Aa5E5993C6"
        ],
        "initialBalanceTotal": 101000000,
        "currentBalances": [
          9208366.100639427,
          12932710.598102087,
          19481612.46892879,
          23916400.29679776
        ],
        "totalBalance": 65539089.46446807,
        "percentage": -14.10196500657518,
        "lpBalances": [
          0.04726123749495429,
          0.03615652613634114,
          0,
          0
        ],
        "totalLPBalance": 0.08341776363129544,
        "poolDOGHoldings": 21217925.878891
      },
      {
        "nickname": "旷谷",
        "addresses": [
          "0x67c1103a967f3150d1fa5e3d70dae8e70c713950"
        ],
        "initialBalanceTotal": 101000000,
        "currentBalances": [
          1e-18
        ],
        "totalBalance": 1e-18,
        "percentage": -100,
        "lpBalances": [
          0
        ],
        "totalLPBalance": 0,
        "poolDOGHoldings": 0
      },
      {
        "nickname": "赢在选择",
        "addresses": [
          "0x30F07E7943669C09fd4bFf545BC6575358c26a92"
        ],
        "initialBalanceTotal": 100285424.9551,
        "currentBalances": [
          62155527.55100492
        ],
        "totalBalance": 62155527.55100492,
        "percentage": 7.915227568937801,
        "lpBalances": [
          0.18111411786062012
        ],
        "totalLPBalance": 0.18111411786062012,
        "poolDOGHoldings": 46067717.007767595
      },
      {
        "nickname": "香香",
        "addresses": [
          "0xA9bb36C922cD1312D0495054F374EF4CbDcd21A0",
          "0x5cE08548C79D59B728Fb9BeEd3c127B7be55512c"
        ],
        "initialBalanceTotal": 100177579,
        "currentBalances": [
          35341819.9573578,
          32859584.837304473
        ],
        "totalBalance": 68201404.79466227,
        "percentage": 3.2392020654095703,
        "lpBalances": [
          0.033598757370271994,
          0.10487225914591232
        ],
        "totalLPBalance": 0.13847101651618432,
        "poolDOGHoldings": 35221128.41338304
      },
      {
        "nickname": "安德鲁",
        "addresses": [
          "0x009cc2efe3f94a446c371093d15ae8d12a3d71ff"
        ],
        "initialBalanceTotal": 100115936.87,
        "currentBalances": [
          76414857.61657074
        ],
        "totalBalance": 76414857.61657074,
        "percentage": 7.912696763145531,
        "lpBalances": [
          0.12432486391873873
        ],
        "totalLPBalance": 0.12432486391873873,
        "poolDOGHoldings": 31622949.749534573
      },
      {
        "nickname": "一骑红尘",
        "addresses": [
          "0xa3d49262df354b6986d071a51bb1ebf950cb66db"
        ],
        "initialBalanceTotal": 100041389.75,
        "currentBalances": [
          100624398.38277274
        ],
        "totalBalance": 100624398.38277274,
        "percentage": 11.608079173071282,
        "lpBalances": [
          0.04336368780011059
        ],
        "totalLPBalance": 0.04336368780011059,
        "poolDOGHoldings": 11029875.095248077
      },
      {
        "nickname": "DOG王",
        "addresses": [
          "0xeceb024766c13347d061b3e6a5d07a4fc86cc03f",
          "0x66bb878e0ecaf689667fd83848e25a0e42fb8441",
          "0xd9f1497619e3467e4196ae64446d590d8cb2a257"
        ],
        "initialBalanceTotal": 100000500,
        "currentBalances": [
          33345727.460798692,
          6154243.997747594,
          6613789.889781509
        ],
        "totalBalance": 46113761.3483278,
        "percentage": 13.436316547905827,
        "lpBalances": [
          0.08774504956154833,
          0,
          0.17693418165866992
        ],
        "totalLPBalance": 0.26467923122021825,
        "poolDOGHoldings": 67323122.38116077
      },
      {
        "nickname": "山河",
        "addresses": [
          "0x71e8b7257873ef4312Cd16DcD0c6CBaeAaBDAA24"
        ],
        "initialBalanceTotal": 100000000,
        "currentBalances": [
          96307952.89039887
        ],
        "totalBalance": 96307952.89039887,
        "percentage": 6.5581936730797885,
        "lpBalances": [
          0.04029857431183711
        ],
        "totalLPBalance": 0.04029857431183711,
        "poolDOGHoldings": 10250240.782680906
      },
      {
        "nickname": "☁️",
        "addresses": [
          "0x9EEAE0DEAaa932ACC49Cfc935Bb997E6779E1E83"
        ],
        "initialBalanceTotal": 100000000,
        "currentBalances": [
          12303247.343077121
        ],
        "totalBalance": 12303247.343077121,
        "percentage": 1.2367525988868922,
        "lpBalances": [
          0.3496399300608482
        ],
        "totalLPBalance": 0.3496399300608482,
        "poolDOGHoldings": 88933505.25580977
      },
      {
        "nickname": "上官允禾",
        "addresses": [
          "0xA6640E4856E4A2f2b754f64AD3dA73FBC724b6Ba"
        ],
        "initialBalanceTotal": 100000000,
        "currentBalances": [
          7472935.146526642
        ],
        "totalBalance": 7472935.146526642,
        "percentage": -0.37970157896396517,
        "lpBalances": [
          0.3622751353150594
        ],
        "totalLPBalance": 0.3622751353150594,
        "poolDOGHoldings": 92147363.27450939
      },
      {
        "nickname": "墨白",
        "addresses": [
          "0x1df0feab384bafab0f16c0f5d24aad5884a584a4",
          "0xea7456d61e26eb2239b6ecd1c27865a6202ea54e",
          "0xff63286dfb1a0eb4d35b862ab95b03e0610e9160",
          "0x3515bd277bb2c5b043388bcaec91a07755a06a33"
        ],
        "initialBalanceTotal": 100000000,
        "currentBalances": [
          46599223.311185695,
          95829798.68999402,
          6068.906477642614,
          5264.0366990143
        ],
        "totalBalance": 142440354.94435638,
        "percentage": 42.440354944356386,
        "lpBalances": [
          0,
          0,
          0,
          0
        ],
        "totalLPBalance": 0,
        "poolDOGHoldings": 0
      },
      {
        "nickname": "跑步二十天",
        "addresses": [
          "0xd65d8de84ce7d92dd97511910233bc10731d8fd0"
        ],
        "initialBalanceTotal": 97863993,
        "currentBalances": [
          83973186.06770504
        ],
        "totalBalance": 83973186.06770504,
        "percentage": 8.466813227095457,
        "lpBalances": [
          0.08718743000963652
        ],
        "totalLPBalance": 0.08718743000963652,
        "poolDOGHoldings": 22176768.436182734
      },
      {
        "nickname": "追梦少年",
        "addresses": [
          "0xe7c842cc81c3019894906476f9d8963881787caa"
        ],
        "initialBalanceTotal": 97554933,
        "currentBalances": [
          88038010.26352297
        ],
        "totalBalance": 88038010.26352297,
        "percentage": -2.657575783068567,
        "lpBalances": [
          0.027222822409691753
        ],
        "totalLPBalance": 0.027222822409691753,
        "poolDOGHoldings": 6924326.461880269
      },
      {
        "nickname": "观明",
        "addresses": [
          "0x3e36e49d20b695a09b503ab3c5860b875f762838",
          "0xe764dc12b1968244e70915949a29575f5a11aa2f"
        ],
        "initialBalanceTotal": 94539367,
        "currentBalances": [
          56939.48026156152,
          0
        ],
        "totalBalance": 56939.48026156152,
        "percentage": -12.314838684576515,
        "lpBalances": [
          0.12445854554243113,
          0.2012251396502839
        ],
        "totalLPBalance": 0.32568368519271507,
        "poolDOGHoldings": 82840056.98026867
      },
      {
        "nickname": "炮兵连长",
        "addresses": [
          "0x4f9059182a44bee2d76927954823055c22701804",
          "0x782df47944e38b102f3cadf78775a1663d4ae5a8",
          "0x7ab43ef55f57bdcdb6e814210b89ea8328a0f67a",
          "0xb4a39abbc482adb85e56e6de509beb99b4d456cb",
          "0x4a4da66a874977143adef4fd07efdadfade78e57",
          "0xfd4c38829463be694e47e347f3c9a0e3bada65e9",
          "0xa485d4d438a3be6265f235a8074e48c9cc034088",
          "0x89eb4d4c75a69004fc76c4225284ebf079650ef6",
          "0x42b361ad83c965ba6b31c2f7283b594a68e8249b"
        ],
        "initialBalanceTotal": 92752164.2,
        "currentBalances": [
          11060900.94926136,
          10948857.738396026,
          10868412.540122919,
          10866610.9491909,
          10971704.101972114,
          10844427.493972074,
          10861977.44797059,
          10860051.296265045,
          10866236.228488348
        ],
        "totalBalance": 98149178.74563938,
        "percentage": 60.62249324616229,
        "lpBalances": [
          0.09991947795384472,
          0.0999239665661995,
          0,
          0,
          0,
          0,
          0,
          0,
          0
        ],
        "totalLPBalance": 0.1998434445200442,
        "poolDOGHoldings": 50831659.93217499
      },
      {
        "nickname": "yoke",
        "addresses": [
          "0x3ec47b5db530883dc6db54064018cc3f6f1c9146"
        ],
        "initialBalanceTotal": 90000000,
        "currentBalances": [
          93719373.31092827
        ],
        "totalBalance": 93719373.31092827,
        "percentage": 4.132637012142522,
        "lpBalances": [
          0
        ],
        "totalLPBalance": 0,
        "poolDOGHoldings": 0
      },
      {
        "nickname": "快乐",
        "addresses": [
          "0xb329b0cb142957F790cdBa44F88b77C500015a7d"
        ],
        "initialBalanceTotal": 87113239.3,
        "currentBalances": [
          98747259.26754397
        ],
        "totalBalance": 98747259.26754397,
        "percentage": 13.355053790938499,
        "lpBalances": [
          0
        ],
        "totalLPBalance": 0,
        "poolDOGHoldings": 0
      },
      {
        "nickname": "dog钻石手嬴荏",
        "addresses": [
          "0xCAf3a882E34A3a7fc08E868463556D0bde240b24"
        ],
        "initialBalanceTotal": 74000000,
        "currentBalances": [
          10480907.053420952
        ],
        "totalBalance": 10480907.053420952,
        "percentage": -32.16273912274589,
        "lpBalances": [
          0.15615297700138708
        ],
        "totalLPBalance": 0.15615297700138708,
        "poolDOGHoldings": 39718665.99574709
      },
      {
        "nickname": "丑到拖网速",
        "addresses": [
          "0x096c1ddf82adfb08ce348e2f8a12900671706edb"
        ],
        "initialBalanceTotal": 62546510,
        "currentBalances": [
          72220662.20333081
        ],
        "totalBalance": 72220662.20333081,
        "percentage": 15.467133503261515,
        "lpBalances": [
          0
        ],
        "totalLPBalance": 0,
        "poolDOGHoldings": 0
      },
      {
        "nickname": "未来(๑]؂[๑）都是晴天",
        "addresses": [
          "0xcf18c19f2d34824f227e4c6900f962b186ebcabb"
        ],
        "initialBalanceTotal": 59806199.9428,
        "currentBalances": [
          62418615.4927424
        ],
        "totalBalance": 62418615.4927424,
        "percentage": 4.368134996774532,
        "lpBalances": [
          0
        ],
        "totalLPBalance": 0,
        "poolDOGHoldings": 0
      },
      {
        "nickname": "玄",
        "addresses": [
          "0x859b301d442258be0006468ebb4de69cb8736bd2"
        ],
        "initialBalanceTotal": 59165033.8135,
        "currentBalances": [
          11500.756273059067
        ],
        "totalBalance": 11500.756273059067,
        "percentage": -38.46702166758103,
        "lpBalances": [
          0.1430841248614506
        ],
        "totalLPBalance": 0.1430841248614506,
        "poolDOGHoldings": 36394506.68055625
      },
      {
        "nickname": "一生平安",
        "addresses": [
          "0x7848400EcCb3D2bccf8D67421569643D06000570"
        ],
        "initialBalanceTotal": 56797518,
        "currentBalances": [
          6990842.25180463
        ],
        "totalBalance": 6990842.25180463,
        "percentage": -45.364618819659604,
        "lpBalances": [
          0.09451542493512065
        ],
        "totalLPBalance": 0.09451542493512065,
        "poolDOGHoldings": 24040698.20846782
      },
      {
        "nickname": "阳光",
        "addresses": [
          "0x8ACdc9BBFeE336e40B797bDE54a8C8205785F29d"
        ],
        "initialBalanceTotal": 51984440.5,
        "currentBalances": [
          54830588.887314305
        ],
        "totalBalance": 54830588.887314305,
        "percentage": 5.4750005192694235,
        "lpBalances": [
          0
        ],
        "totalLPBalance": 0,
        "poolDOGHoldings": 0
      },
      {
        "nickname": "曾经的自己",
        "addresses": [
          "0xEA6a7cD780a941c0b9c2Dd7d1B5F7f4C51AA3dCA"
        ],
        "initialBalanceTotal": 51700000,
        "currentBalances": [
          21874629.672744524
        ],
        "totalBalance": 21874629.672744524,
        "percentage": -57.68930430803767,
        "lpBalances": [
          0
        ],
        "totalLPBalance": 0,
        "poolDOGHoldings": 0
      },
      {
        "nickname": "ゅ 煙誮洅躾︵鈈濄橓間づ",
        "addresses": [
          "0xa73c95FEDa4C2dE3009dBA67B2d58981bF4AB073"
        ],
        "initialBalanceTotal": 50762682,
        "currentBalances": [
          43493213.54716069
        ],
        "totalBalance": 43493213.54716069,
        "percentage": -14.320497196817353,
        "lpBalances": [
          0
        ],
        "totalLPBalance": 0,
        "poolDOGHoldings": 0
      },
      {
        "nickname": "金马影帝",
        "addresses": [
          "0xcEf0b9c76CA29A58220A761ae37D12885C230505"
        ],
        "initialBalanceTotal": 50053651,
        "currentBalances": [
          45537858.30349552
        ],
        "totalBalance": 45537858.30349552,
        "percentage": 7.257928577260446,
        "lpBalances": [
          0.03203622453985678
        ],
        "totalLPBalance": 0.03203622453985678,
        "poolDOGHoldings": 8148650.936395692
      },
      {
        "nickname": "绅士",
        "addresses": [
          "0x923A9C9fa04685648cbb775116c20Db763D1af22"
        ],
        "initialBalanceTotal": 50000000,
        "currentBalances": [
          60524829.15618645
        ],
        "totalBalance": 60524829.15618645,
        "percentage": 21.049658312372895,
        "lpBalances": [
          0
        ],
        "totalLPBalance": 0,
        "poolDOGHoldings": 0
      },
      {
        "nickname": "清宁",
        "addresses": [
          "0x22682a4fd1bc5aa023d3410fd6775f7a12834a66"
        ],
        "initialBalanceTotal": 49000000,
        "currentBalances": [
          34119462.503579
        ],
        "totalBalance": 34119462.503579,
        "percentage": 5.21402607712177,
        "lpBalances": [
          0.06854689479878529
        ],
        "totalLPBalance": 0.06854689479878529,
        "poolDOGHoldings": 17435410.274210665
      },
      {
        "nickname": "双旗协议赣州脐橙大叔",
        "addresses": [
          "0xB22982aF7467Caa163D03f75f20951Db21c89976"
        ],
        "initialBalanceTotal": 45262963,
        "currentBalances": [
          45490655.59829639
        ],
        "totalBalance": 45490655.59829639,
        "percentage": 0.5030439529475544,
        "lpBalances": [
          0
        ],
        "totalLPBalance": 0,
        "poolDOGHoldings": 0
      },
      {
        "nickname": "天雨",
        "addresses": [
          "0x1747c3037ec12510610de0ebe7138c8b55d67f73"
        ],
        "initialBalanceTotal": 45000000,
        "currentBalances": [
          71048.10130128326
        ],
        "totalBalance": 71048.10130128326,
        "percentage": -50.34156696233422,
        "lpBalances": [
          0.08757459518577365
        ],
        "totalLPBalance": 0.08757459518577365,
        "poolDOGHoldings": 22275246.76564832
      },
      {
        "nickname": "皇总",
        "addresses": [
          "0xd1e6245B3EF1D2c5d51263E2d379F9e87FF04B5B"
        ],
        "initialBalanceTotal": 41765271.55,
        "currentBalances": [
          10414680.775824651
        ],
        "totalBalance": 10414680.775824651,
        "percentage": -75.06377813596508,
        "lpBalances": [
          0
        ],
        "totalLPBalance": 0,
        "poolDOGHoldings": 0
      },
      {
        "nickname": "With Headphones",
        "addresses": [
          "0x3da1f6c028ebc007f7d2beb959d1b7ecf29c295e"
        ],
        "initialBalanceTotal": 41359845,
        "currentBalances": [
          62429428.6342174
        ],
        "totalBalance": 62429428.6342174,
        "percentage": 50.942124261387825,
        "lpBalances": [
          0
        ],
        "totalLPBalance": 0,
        "poolDOGHoldings": 0
      },
      {
        "nickname": "素雅",
        "addresses": [
          "0x85017f9f1860ad5e27a18566fbc7917f4fad2032"
        ],
        "initialBalanceTotal": 41000000,
        "currentBalances": [
          30834585.33936847
        ],
        "totalBalance": 30834585.33936847,
        "percentage": 156.62718984843704,
        "lpBalances": [
          0.2924332497061898
        ],
        "totalLPBalance": 0.2924332497061898,
        "poolDOGHoldings": 74382562.4984907
      },
      {
        "nickname": "可乐",
        "addresses": [
          "0x48ec8991cd72d7b63a4ba6f0e550cb2e8782948c"
        ],
        "initialBalanceTotal": 40010261.12,
        "currentBalances": [
          30326221.67095481
        ],
        "totalBalance": 30326221.67095481,
        "percentage": -24.203889647209554,
        "lpBalances": [
          0
        ],
        "totalLPBalance": 0,
        "poolDOGHoldings": 0
      },
      {
        "nickname": "仓位又不见了",
        "addresses": [
          "0xb76fbb9c4c9afc39a5e87f6dad848fb999146e46"
        ],
        "initialBalanceTotal": 40000000,
        "currentBalances": [
          24463984.827553935
        ],
        "totalBalance": 24463984.827553935,
        "percentage": -5.340381664083898,
        "lpBalances": [
          0.052681236123894276
        ],
        "totalLPBalance": 0.052681236123894276,
        "poolDOGHoldings": 13399862.50681251
      },
      {
        "nickname": "永恒",
        "addresses": [
          "0x681c67Eafdee6B3080C84ed67b2d935655EA4B04"
        ],
        "initialBalanceTotal": 40000000,
        "currentBalances": [
          12639244.597919498
        ],
        "totalBalance": 12639244.597919498,
        "percentage": -68.40188850520126,
        "lpBalances": [
          0
        ],
        "totalLPBalance": 0,
        "poolDOGHoldings": 0
      },
      {
        "nickname": "雪狼",
        "addresses": [
          "0xd69dc3f6e449f3679a9e0b904c28f8554140ca60"
        ],
        "initialBalanceTotal": 38000000,
        "currentBalances": [
          11831543.933734028
        ],
        "totalBalance": 11831543.933734028,
        "percentage": -21.71312871224943,
        "lpBalances": [
          0.07044208979659203
        ],
        "totalLPBalance": 0.07044208979659203,
        "poolDOGHoldings": 17917467.15561119
      },
      {
        "nickname": "城市/ht 日记",
        "addresses": [
          "0x751c303562ec9b4d9b7e9f90cd94506e40b0d62a",
          "0x1e435da43375a4ed8e72a8c3f8154e01ace90652"
        ],
        "initialBalanceTotal": 36577296,
        "currentBalances": [
          69306.27802928118,
          11025712.03325059
        ],
        "totalBalance": 11095018.311279872,
        "percentage": 176.68706980666246,
        "lpBalances": [
          0.1401938574571417,
          0.21406997946552433
        ],
        "totalLPBalance": 0.35426383692266605,
        "poolDOGHoldings": 90109630.20562968
      },
      {
        "nickname": "南方种植园",
        "addresses": [
          "0xf439bd457304a9f49ecffefb46450993d5bc5769"
        ],
        "initialBalanceTotal": 35000000,
        "currentBalances": [
          265740.7466415435
        ],
        "totalBalance": 265740.7466415435,
        "percentage": -36.69754969513573,
        "lpBalances": [
          0.08606046625465168
        ],
        "totalLPBalance": 0.08606046625465168,
        "poolDOGHoldings": 21890116.860060953
      },
      {
        "nickname": "暂停的失忆",
        "addresses": [
          "0xc06433b647fF520e5782D33D3e7b7b4D0D405B97"
        ],
        "initialBalanceTotal": 33237400,
        "currentBalances": [
          34263466.14996864
        ],
        "totalBalance": 34263466.14996864,
        "percentage": 3.0870830749957547,
        "lpBalances": [
          0
        ],
        "totalLPBalance": 0,
        "poolDOGHoldings": 0
      },
      {
        "nickname": "我的未来不是梦",
        "addresses": [
          "0xefff2973f53cda207d690ed4de8f2963d471e707",
          "0x800e2d7603d28e2d0bac5ef118a893158d2b87e7"
        ],
        "initialBalanceTotal": 32641670.4921,
        "currentBalances": [
          435931.2651199247,
          3.6882664078107292
        ],
        "totalBalance": 435934.9533863325,
        "percentage": -41.92412608117077,
        "lpBalances": [
          0.017469194634022422,
          0.05534567173362245
        ],
        "totalLPBalance": 0.07281486636764486,
        "poolDOGHoldings": 18521000.446605347
      },
      {
        "nickname": "天天好心情",
        "addresses": [
          "0xab5b0628F7f3c0CDdE9391abdF0Ff359C9B78636"
        ],
        "initialBalanceTotal": 31296418.3456,
        "currentBalances": [
          26557.91591093306
        ],
        "totalBalance": 26557.91591093306,
        "percentage": -40.745246246397116,
        "lpBalances": [
          0.07280329706367715
        ],
        "totalLPBalance": 0.07280329706367715,
        "poolDOGHoldings": 18518057.708471745
      },
      {
        "nickname": "虚竹",
        "addresses": [
          "0xa7e86b6afc20249aA3dEB6760529c8dd890CE7fd"
        ],
        "initialBalanceTotal": 30601311,
        "currentBalances": [
          0
        ],
        "totalBalance": 0,
        "percentage": -100,
        "lpBalances": [
          0
        ],
        "totalLPBalance": 0,
        "poolDOGHoldings": 0
      },
      {
        "nickname": "空调不够冷",
        "addresses": [
          "0x8342d572e84fdcf9a85a1b119b59b3ef4d8621ee"
        ],
        "initialBalanceTotal": 30000000,
        "currentBalances": [
          31664668.42689447
        ],
        "totalBalance": 31664668.42689447,
        "percentage": 5.548894756314904,
        "lpBalances": [
          0
        ],
        "totalLPBalance": 0,
        "poolDOGHoldings": 0
      },
      {
        "nickname": "Mr丶張",
        "addresses": [
          "0x66db43f3672dee8629f042e08c639efd9de4dd0d"
        ],
        "initialBalanceTotal": 30000000,
        "currentBalances": [
          2233898.795162511
        ],
        "totalBalance": 2233898.795162511,
        "percentage": -35.7943983626981,
        "lpBalances": [
          0.06694431287921951
        ],
        "totalLPBalance": 0.06694431287921951,
        "poolDOGHoldings": 17027781.69602806
      },
      {
        "nickname": "张幸英",
        "addresses": [
          "0x736646b6feb11874c515757ce377ddfc7e9c666b"
        ],
        "initialBalanceTotal": 29565814,
        "currentBalances": [
          30603452.156560563
        ],
        "totalBalance": 30603452.156560563,
        "percentage": 3.50958764930525,
        "lpBalances": [
          0
        ],
        "totalLPBalance": 0,
        "poolDOGHoldings": 0
      },
      {
        "nickname": "不正经的正经人",
        "addresses": [
          "0xc3584c580db43929bc1ba6767b37ee51f79c8655"
        ],
        "initialBalanceTotal": 29501345,
        "currentBalances": [
          11185851.280085742
        ],
        "totalBalance": 11185851.280085742,
        "percentage": -60.34029866025197,
        "lpBalances": [
          0.002021934601619358
        ],
        "totalLPBalance": 0.002021934601619358,
        "poolDOGHoldings": 514294.0381229482
      },
      {
        "nickname": "汽修",
        "addresses": [
          "0x6684220508518560ba545148d4b2eb38b420934a"
        ],
        "initialBalanceTotal": 29049259,
        "currentBalances": [
          16846757.246111184
        ],
        "totalBalance": 16846757.246111184,
        "percentage": 11.370220852569997,
        "lpBalances": [
          0.06095936803961803
        ],
        "totalLPBalance": 0.06095936803961803,
        "poolDOGHoldings": 15505466.658223884
      },
      {
        "nickname": "得信",
        "addresses": [
          "0x0878d43fF64014eeA652d8A3Bb24DE2BB89af105"
        ],
        "initialBalanceTotal": 27986507,
        "currentBalances": [
          29326568.712980773
        ],
        "totalBalance": 29326568.712980773,
        "percentage": 4.788242108887591,
        "lpBalances": [
          0
        ],
        "totalLPBalance": 0,
        "poolDOGHoldings": 0
      },
      {
        "nickname": "细雨飞撒",
        "addresses": [
          "0xc51118dd63f361f8a706d8179a3b91e7712485dc"
        ],
        "initialBalanceTotal": 27592374,
        "currentBalances": [
          13780827.220278498
        ],
        "totalBalance": 13780827.220278498,
        "percentage": -50.05566675676947,
        "lpBalances": [
          0
        ],
        "totalLPBalance": 0,
        "poolDOGHoldings": 0
      },
      {
        "nickname": "百",
        "addresses": [
          "0x7f17bec72dc1b938dd6e0b3af6442bc1e9d89017"
        ],
        "initialBalanceTotal": 26000000,
        "currentBalances": [
          9253031.630957128
        ],
        "totalBalance": 9253031.630957128,
        "percentage": -29.23922056525284,
        "lpBalances": [
          0.03595244662160265
        ],
        "totalLPBalance": 0.03595244662160265,
        "poolDOGHoldings": 9144771.022077132
      },
      {
        "nickname": "清",
        "addresses": [
          "0x17f9a381844980c2a7313f06cec717e7f0af0499"
        ],
        "initialBalanceTotal": 25910000,
        "currentBalances": [
          39603.67822150985
        ],
        "totalBalance": 39603.67822150985,
        "percentage": 108.45759086282645,
        "lpBalances": [
          0.21218866475663822
        ],
        "totalLPBalance": 0.21218866475663822,
        "poolDOGHoldings": 53971758.114336826
      },
      {
        "nickname": "钇丞",
        "addresses": [
          "0x6A53FBf66c1c7FE95F6B740A9Ed4B81597712c3E"
        ],
        "initialBalanceTotal": 25000000,
        "currentBalances": [
          70540493.01679546
        ],
        "totalBalance": 70540493.01679546,
        "percentage": 182.16197206718184,
        "lpBalances": [
          0
        ],
        "totalLPBalance": 0,
        "poolDOGHoldings": 0
      },
      {
        "nickname": "子玲",
        "addresses": [
          "0xF8155361cFF0A4b3073cF5CafF2bA4e7B610570E"
        ],
        "initialBalanceTotal": 24786625,
        "currentBalances": [
          21128760.955876168
        ],
        "totalBalance": 21128760.955876168,
        "percentage": -14.757410676620283,
        "lpBalances": [
          0
        ],
        "totalLPBalance": 0,
        "poolDOGHoldings": 0
      },
      {
        "nickname": "王梓【RWA】）",
        "addresses": [
          "0x2A8db2bD281687B43f532e95791C824A7681f9C4"
        ],
        "initialBalanceTotal": 24371135,
        "currentBalances": [
          201342.00070458403
        ],
        "totalBalance": 201342.00070458403,
        "percentage": -77.17243692397375,
        "lpBalances": [
          0.021080550873312388
        ],
        "totalLPBalance": 0.021080550873312388,
        "poolDOGHoldings": 5361994.213763928
      },
      {
        "nickname": "欧阳锋",
        "addresses": [
          "0xbFe7ca9b5388D9f3693BBFdb13E24aB005FB8EFf"
        ],
        "initialBalanceTotal": 24000000,
        "currentBalances": [
          0
        ],
        "totalBalance": 0,
        "percentage": -100,
        "lpBalances": [
          0
        ],
        "totalLPBalance": 0,
        "poolDOGHoldings": 0
      },
      {
        "nickname": "天",
        "addresses": [
          "0x407df78644b3f815868385886a40f3ea8e659ff0"
        ],
        "initialBalanceTotal": 24000000,
        "currentBalances": [
          26466594.149702035
        ],
        "totalBalance": 26466594.149702035,
        "percentage": 10.277475623758479,
        "lpBalances": [
          0
        ],
        "totalLPBalance": 0,
        "poolDOGHoldings": 0
      },
      {
        "nickname": "钻石DOG",
        "addresses": [
          "0xfbdd6e0a6fd057b3fee46244c7c2726f8a0aff1a",
          "0x1aa8d6395F769989Cd5a64DAD562863BB1aBB0ff"
        ],
        "initialBalanceTotal": 23803093,
        "currentBalances": [
          26113.76106032492,
          13803046.582983358
        ],
        "totalBalance": 13829160.344043683,
        "percentage": -14.285056192518681,
        "lpBalances": [
          0.025844136317637073,
          0
        ],
        "totalLPBalance": 0.025844136317637073,
        "poolDOGHoldings": 6573647.445348837
      },
      {
        "nickname": "柚子哥",
        "addresses": [
          "0x7d51c88e306ecc6ba812cc1bc52c9c040b1ebdf7"
        ],
        "initialBalanceTotal": 23561975.2,
        "currentBalances": [
          24936785.128024302
        ],
        "totalBalance": 24936785.128024302,
        "percentage": 5.834867053184502,
        "lpBalances": [
          0
        ],
        "totalLPBalance": 0,
        "poolDOGHoldings": 0
      },
      {
        "nickname": "给生活加点糖",
        "addresses": [
          "0x5ce24AC37FCAFdf22F0CeEB097c0C266FAD13319"
        ],
        "initialBalanceTotal": 22950000,
        "currentBalances": [
          23888736.24665629
        ],
        "totalBalance": 23888736.24665629,
        "percentage": 4.090354015931553,
        "lpBalances": [
          0
        ],
        "totalLPBalance": 0,
        "poolDOGHoldings": 0
      },
      {
        "nickname": "是以前",
        "addresses": [
          "0xe53052a6a96515e5f7740869bcd58415987c1fbb"
        ],
        "initialBalanceTotal": 22866522.69653,
        "currentBalances": [
          12137942.441174781
        ],
        "totalBalance": 12137942.441174781,
        "percentage": -46.91828485571741,
        "lpBalances": [
          0
        ],
        "totalLPBalance": 0,
        "poolDOGHoldings": 0
      },
      {
        "nickname": "布朗船长",
        "addresses": [
          "0x0e0a91b2c6a179841fe116f338c7a1e50bcd01c1",
          "0xb3502f30ba7ac2ff5293453d6f0880e9ae581424"
        ],
        "initialBalanceTotal": 22850472,
        "currentBalances": [
          13546847.349794934,
          10554730.92646055
        ],
        "totalBalance": 24101578.27625548,
        "percentage": 5.475187892204069,
        "lpBalances": [
          0,
          0
        ],
        "totalLPBalance": 0,
        "poolDOGHoldings": 0
      },
      {
        "nickname": "草民吃藕",
        "addresses": [
          "0xfb31db250165f809997e3b67d6b769e15e1218d2"
        ],
        "initialBalanceTotal": 22398645,
        "currentBalances": [
          24628678.47412398
        ],
        "totalBalance": 24628678.47412398,
        "percentage": 9.956108836601414,
        "lpBalances": [
          0
        ],
        "totalLPBalance": 0,
        "poolDOGHoldings": 0
      },
      {
        "nickname": "仙儿",
        "addresses": [
          "0xe5814c4063022DFE2B77eDd087DAb456D40c3a14"
        ],
        "initialBalanceTotal": 22249621.9321,
        "currentBalances": [
          20375411.840235185
        ],
        "totalBalance": 20375411.840235185,
        "percentage": -8.42355927477965,
        "lpBalances": [
          0
        ],
        "totalLPBalance": 0,
        "poolDOGHoldings": 0
      },
      {
        "nickname": "卫东",
        "addresses": [
          "0x25A5D14ED1a08fa65E50C711CA60De260d339dA4"
        ],
        "initialBalanceTotal": 21933408,
        "currentBalances": [
          35797291.042634286
        ],
        "totalBalance": 35797291.042634286,
        "percentage": 63.20897802400013,
        "lpBalances": [
          0
        ],
        "totalLPBalance": 0,
        "poolDOGHoldings": 0
      },
      {
        "nickname": "静慈",
        "addresses": [
          "0x288EDeb44D61d6429516095A829b4dD974196f21"
        ],
        "initialBalanceTotal": 21926838,
        "currentBalances": [
          6032256.355374553
        ],
        "totalBalance": 6032256.355374553,
        "percentage": -72.48916439582145,
        "lpBalances": [
          0
        ],
        "totalLPBalance": 0,
        "poolDOGHoldings": 0
      },
      {
        "nickname": "嘟嘟",
        "addresses": [
          "0x17b7210d8a802fc6a536936aa40ccf9db920605c"
        ],
        "initialBalanceTotal": 21900000,
        "currentBalances": [
          5186480.931703856
        ],
        "totalBalance": 5186480.931703856,
        "percentage": -76.31743866801892,
        "lpBalances": [
          0
        ],
        "totalLPBalance": 0,
        "poolDOGHoldings": 0
      },
      {
        "nickname": "打dog小兵3947068284",
        "addresses": [
          "0x45c63296173e9d737d43866ec78ae9163e700d15"
        ],
        "initialBalanceTotal": 21780000,
        "currentBalances": [
          18035129.93933646
        ],
        "totalBalance": 18035129.93933646,
        "percentage": 3.0282740873244958,
        "lpBalances": [
          0.017315903025535328
        ],
        "totalLPBalance": 0.017315903025535328,
        "poolDOGHoldings": 4404428.156882816
      },
      {
        "nickname": "渔夫",
        "addresses": [
          "0x7c7dc603fa553168933605728c40d14b1680b010"
        ],
        "initialBalanceTotal": 21699222.1648,
        "currentBalances": [
          18609.633020422305
        ],
        "totalBalance": 18609.633020422305,
        "percentage": 9.152392118679392,
        "lpBalances": [
          0.09304470786428967
        ],
        "totalLPBalance": 0.09304470786428967,
        "poolDOGHoldings": 23666610.431005463
      },
      {
        "nickname": "有若",
        "addresses": [
          "0x7ed2E03E45E0E16d268BC01B39053E166b29DdB1"
        ],
        "initialBalanceTotal": 21307781,
        "currentBalances": [
          21549047.12829451
        ],
        "totalBalance": 21549047.12829451,
        "percentage": 4.0864857799263525,
        "lpBalances": [
          0.002474759138871206
        ],
        "totalLPBalance": 0.002474759138871206,
        "poolDOGHoldings": 629473.3122883401
      },
      {
        "nickname": "转运丹",
        "addresses": [
          "0x58a5483e35F0E67F367E30811Efc3bF0c2ecE4C9"
        ],
        "initialBalanceTotal": 21196455,
        "currentBalances": [
          22566737.74932417
        ],
        "totalBalance": 22566737.74932417,
        "percentage": 6.464678878256619,
        "lpBalances": [
          0
        ],
        "totalLPBalance": 0,
        "poolDOGHoldings": 0
      },
      {
        "nickname": "美心木门",
        "addresses": [
          "0x2f7427D2007aC9b1F449aAB67498E0caa579eeeC",
          "0x62F42b066f0C88e4668a56015CDF5204FFdc063B"
        ],
        "initialBalanceTotal": 21190777.8431,
        "currentBalances": [
          11394026.33547099,
          10872223.15313955
        ],
        "totalBalance": 22266249.48861054,
        "percentage": 5.075187203950266,
        "lpBalances": [
          0,
          0
        ],
        "totalLPBalance": 0,
        "poolDOGHoldings": 0
      },
      {
        "nickname": "翡翠遗失在巴拉瑞",
        "addresses": [
          "0xDade000DCB6FD94db067ad10a1df5E6d8f825f36"
        ],
        "initialBalanceTotal": 21000000,
        "currentBalances": [
          5756770.918549107
        ],
        "totalBalance": 5756770.918549107,
        "percentage": 6.754004645151432,
        "lpBalances": [
          0.06550456065633715
        ],
        "totalLPBalance": 0.06550456065633715,
        "poolDOGHoldings": 16661570.056932695
      },
      {
        "nickname": "追梦人",
        "addresses": [
          "0x21e79e6b92a6d06ee05ed915800aad024f75690c",
          "0x37f060170b552d6664ba546be166cc85bb02ebbe"
        ],
        "initialBalanceTotal": 20930930.193,
        "currentBalances": [
          28839.5772252908,
          0
        ],
        "totalBalance": 28839.5772252908,
        "percentage": -54.04745127796278,
        "lpBalances": [
          0.037700716131608684,
          0
        ],
        "totalLPBalance": 0.037700716131608684,
        "poolDOGHoldings": 9589456.317688635
      },
      {
        "nickname": "未来不是梦",
        "addresses": [
          "0x4e9a53A24DCa47F2A13edB22C428Ce846B782300"
        ],
        "initialBalanceTotal": 20914636.2,
        "currentBalances": [
          21983405.435748097
        ],
        "totalBalance": 21983405.435748097,
        "percentage": 5.110149779933047,
        "lpBalances": [
          0
        ],
        "totalLPBalance": 0,
        "poolDOGHoldings": 0
      },
      {
        "nickname": "Leon",
        "addresses": [
          "0x7a1f9493256b40f6273ff9271fe7a736e68c845b"
        ],
        "initialBalanceTotal": 20838717.2253,
        "currentBalances": [
          28722976.145697143
        ],
        "totalBalance": 28722976.145697143,
        "percentage": 37.83466532587224,
        "lpBalances": [
          0
        ],
        "totalLPBalance": 0,
        "poolDOGHoldings": 0
      },
      {
        "nickname": "千与千寻",
        "addresses": [
          "0xc878db43b55ced1261c5f000bee169b5a69c98bf"
        ],
        "initialBalanceTotal": 20780000,
        "currentBalances": [
          21506459.078938413
        ],
        "totalBalance": 21506459.078938413,
        "percentage": 3.4959532191453966,
        "lpBalances": [
          0
        ],
        "totalLPBalance": 0,
        "poolDOGHoldings": 0
      },
      {
        "nickname": "东财",
        "addresses": [
          "0x54585df5015ad49ab21c92d5fdd9f81f4c3f82e4"
        ],
        "initialBalanceTotal": 20639845,
        "currentBalances": [
          20135212.35344079
        ],
        "totalBalance": 20135212.35344079,
        "percentage": -2.4449439739455827,
        "lpBalances": [
          0
        ],
        "totalLPBalance": 0,
        "poolDOGHoldings": 0
      },
      {
        "nickname": "众鑫社区锁先生",
        "addresses": [
          "0x273A16f8968D3f1c31C98609eEDf26be91B89e7E",
          "0xB1Ca2eDfBA5e18445B254e98cb7b5dcA128f6666"
        ],
        "initialBalanceTotal": 20270000,
        "currentBalances": [
          10996209.569516392,
          5
        ],
        "totalBalance": 10996214.569516392,
        "percentage": 10.739776597432407,
        "lpBalances": [
          0,
          0.0450183007323306
        ],
        "totalLPBalance": 0.0450183007323306,
        "poolDOGHoldings": 11450738.146783154
      },
      {
        "nickname": "胡云飞",
        "addresses": [
          "0x217796F3fE056844e03c181Ab4E73b4B8629f30c"
        ],
        "initialBalanceTotal": 20184078,
        "currentBalances": [
          20719115.49677799
        ],
        "totalBalance": 20719115.49677799,
        "percentage": 3.793934434980014,
        "lpBalances": [
          0.00090712196465453
        ],
        "totalLPBalance": 0.00090712196465453,
        "poolDOGHoldings": 230733.18884723616
      },
      {
        "nickname": "真善美",
        "addresses": [
          "0xafd4b7762b4c7f70fe022c0db9564d2d33ec1e40"
        ],
        "initialBalanceTotal": 20173002,
        "currentBalances": [
          15293440.74878161
        ],
        "totalBalance": 15293440.74878161,
        "percentage": 28.469790261635207,
        "lpBalances": [
          0.04176317420259198
        ],
        "totalLPBalance": 0.04176317420259198,
        "poolDOGHoldings": 10622772.610093866
      },
      {
        "nickname": "喜乐人生",
        "addresses": [
          "0xee642b9ac75e47dc55b93a706782abab9a7e4a8e"
        ],
        "initialBalanceTotal": 20100000,
        "currentBalances": [
          0
        ],
        "totalBalance": 0,
        "percentage": -57.696995963359655,
        "lpBalances": [
          0.03342896117012617
        ],
        "totalLPBalance": 0.03342896117012617,
        "poolDOGHoldings": 8502903.81136471
      },
      {
        "nickname": "逗霸",
        "addresses": [
          "0x0588f6F728635BA9FB0DCB8eF1C01aB5A56f801c",
          "0x4a99ed0d8e8cfd6149a0d22233be0d5bea0fba6a"
        ],
        "initialBalanceTotal": 20071225,
        "currentBalances": [
          0,
          0.03681992891698604
        ],
        "totalBalance": 0.03681992891698604,
        "percentage": 244.30946229885478,
        "lpBalances": [
          0.08768452940263323,
          0.18400847229181963
        ],
        "totalLPBalance": 0.2716930016944529,
        "poolDOGHoldings": 69107126.83747338
      },
      {
        "nickname": "追逐",
        "addresses": [
          "0x8ad837f28e41C1Ee9f71930E1D3D5DeeaC4e2f06",
          "0xe8e67897a0389b82d988630a2ec5de9e0fa07323"
        ],
        "initialBalanceTotal": 20023059.08,
        "currentBalances": [
          376109.24596759013,
          8337070.142459617
        ],
        "totalBalance": 8713179.388427207,
        "percentage": -17.018018666072653,
        "lpBalances": [
          0.03106790527003388,
          0
        ],
        "totalLPBalance": 0.03106790527003388,
        "poolDOGHoldings": 7902351.759819636
      },
      {
        "nickname": "魔虫",
        "addresses": [
          "0x2a5e034c80671b622cc3cf3c1fe4f08c00f36c48"
        ],
        "initialBalanceTotal": 20000000,
        "currentBalances": [
          0.000005715564962858
        ],
        "totalBalance": 0.000005715564962858,
        "percentage": 233.9676929892963,
        "lpBalances": [
          0.2625971853543291
        ],
        "totalLPBalance": 0.2625971853543291,
        "poolDOGHoldings": 66793538.59785354
      },
      {
        "nickname": "小趴菜",
        "addresses": [
          "0xDF015F69988bF2395631415d6D9a121A7adf0B09"
        ],
        "initialBalanceTotal": 20000000,
        "currentBalances": [
          10503607.985663496
        ],
        "totalBalance": 10503607.985663496,
        "percentage": 7.410569664755295,
        "lpBalances": [
          0.043161731234376034
        ],
        "totalLPBalance": 0.043161731234376034,
        "poolDOGHoldings": 10978505.947287563
      },
      {
        "nickname": "三好",
        "addresses": [
          "0xA6b47715466269c6835fC834A87ed447bA26FbF6"
        ],
        "initialBalanceTotal": 20000000,
        "currentBalances": [
          20692555.92565619
        ],
        "totalBalance": 20692555.92565619,
        "percentage": 3.4627796282809418,
        "lpBalances": [
          0
        ],
        "totalLPBalance": 0,
        "poolDOGHoldings": 0
      },
      {
        "nickname": "Foever",
        "addresses": [
          "0x98e5b334601f3ca477f4738c1f0ca108c1f9de7f",
          "0xF3C135FC7e014b26F64c4f074569d59078EfE488"
        ],
        "initialBalanceTotal": 20000000,
        "currentBalances": [
          15343422.713760778,
          7676713.228404047
        ],
        "totalBalance": 23020135.942164823,
        "percentage": 15.100679710824117,
        "lpBalances": [
          0,
          0
        ],
        "totalLPBalance": 0,
        "poolDOGHoldings": 0
      },
      {
        "nickname": "小雨滴",
        "addresses": [
          "0x1c7bb3f9A4899E05D82B96b8346A1ed606C5A37E",
          "0xb852431e7B98531f68964204F6c2f23512D82388",
          "0x0Af9D6160093864a971bb07941eBbfa06902d539",
          "0xcD2a576218a86e0B9B5956D35A82f4909160BaB7"
        ],
        "initialBalanceTotal": 21373976.9876,
        "currentBalances": [
          5606375.547669262,
          5999130.054800333,
          5527980.061118826,
          5540936.267985651
        ],
        "totalBalance": 22674421.93157407,
        "percentage": 6.08424414758431,
        "lpBalances": [
          0,
          0,
          0,
          0
        ],
        "totalLPBalance": 0,
        "poolDOGHoldings": 0
      },
      {
        "nickname": "魔虫",
        "addresses": [
          "0x2a5e034c80671b622cc3cf3c1fe4f08c00f36c48"
        ],
        "initialBalanceTotal": 50000000,
        "currentBalances": [
          0.000005715564962858
        ],
        "totalBalance": 0.000005715564962858,
        "percentage": 33.587077195718514,
        "lpBalances": [
          0.2625971853543291
        ],
        "totalLPBalance": 0.2625971853543291,
        "poolDOGHoldings": 66793538.59785354
      },
      {
        "nickname": "太阳",
        "addresses": [
          "0x834510aa808c4f58bc0611667fa2ea803e8bee2a"
        ],
        "initialBalanceTotal": 90000000,
        "currentBalances": [
          0
        ],
        "totalBalance": 0,
        "percentage": 27.24078677088072,
        "lpBalances": [
          0.4502196747282325
        ],
        "totalLPBalance": 0.4502196747282325,
        "poolDOGHoldings": 114516708.09379265
      },
      {
        "nickname": "风雨同舟",
        "addresses": [
          "0x7c9657ad56861e44E7531601c0689C8ffDcb59b9",
          "0x39Ac354FD4c6115dEb72263ED44a31a9eACC0C9F"
        ],
        "initialBalanceTotal": 0,
        "currentBalances": [
          541771.1443344953,
          618695.1078056856
        ],
        "totalBalance": 1160466.252140181,
        "percentage": 0,
        "lpBalances": [
          0.08190888509150933,
          0.10538140945041348
        ],
        "totalLPBalance": 0.1872902945419228,
        "poolDOGHoldings": 47638673.28055902
      },
      {
        "nickname": "M丶張",
        "addresses": [
          "0x66db43f3672dee8629f042e08c639efd9de4dd0d",
          "0xb8558cc872b20c271e4025972c54fc76efd542b8"
        ],
        "initialBalanceTotal": 0,
        "currentBalances": [
          2233898.795162511,
          193106.56022634413
        ],
        "totalBalance": 2427005.355388855,
        "percentage": 0,
        "lpBalances": [
          0.06694431287921951,
          0.06423075811621129
        ],
        "totalLPBalance": 0.1311750709954308,
        "poolDOGHoldings": 33365350.64451347
      }
    ],
    "lastUpdate": "2025-12-23T10:00:25.823Z",
    "totalUsers": 131,
    "totalAddresses": 191,
    "poolStats": {
      "poolAddress": "0x41027D3CaCc14F35Abd387B7350c05247e9Ac646",
      "poolDOGReserve": 11500288820.833782,
      "lpTokenSupply": 45.213108011765904,
      "lpTokenSymbol": "Pot-LP",
      "totalPoolDOGHoldings": 7708462633.739566,
      "usersWithPoolHoldings": 85,
      "unallocatedDOG": 3791826187.0942163,
      "unallocatedPercent": 32.97157355061371
    }
  }
}